README.md
setup.py
quantile_transformer_tf/__init__.py
quantile_transformer_tf/interpolate_tf.py
quantile_transformer_tf/quantile_transform_tf.py
quantile_transformer_tf.egg-info/PKG-INFO
quantile_transformer_tf.egg-info/SOURCES.txt
quantile_transformer_tf.egg-info/dependency_links.txt
quantile_transformer_tf.egg-info/requires.txt
quantile_transformer_tf.egg-info/top_level.txt