Metadata-Version: 1.1
Name: quantile-transformer-tf
Version: 1.1
Summary: An implementation of QuantileTransformer in tensorflow
Home-page: https://github.com/yandexdataschool/QuantileTransformerTF
Author: Nikita Kazeev
Author-email: nikita.kazeev@cern.ch
License: Apache 2.0
Platform: UNKNOWN
Classifier: Development Status :: 4 - Beta
Classifier: Intended Audience :: Science/Research
Classifier: License :: OSI Approved :: Apache Software License
Classifier: Programming Language :: Python :: 3
